setup.py
wordsmiths/__init__.py
wordsmiths/ot.py
wordsmiths.egg-info/PKG-INFO
wordsmiths.egg-info/SOURCES.txt
wordsmiths.egg-info/dependency_links.txt
wordsmiths.egg-info/top_level.txt