Metadata-Version: 1.1
Name: wordsmiths
Version: 0.1.2
Summary: Operational Transformation implementation in Python (WIP)
Home-page: https://github.com/kingdion/wordsmiths
Author: D. Misic
Author-email: dion@gmail.com
License: MIT
Platform: UNKNOWN
Classifier: Development Status :: 3 - Alpha
Classifier: Intended Audience :: Developers
Classifier: Topic :: Software Development :: Build Tools
Classifier: License :: OSI Approved :: MIT License
Classifier: Programming Language :: Python :: 3.6
